goalEDP/__init__.py
goalEDP/core.py
goalEDP/explainers/__init__.py
goalEDP/explainers/simple_explainer.py
goalEDP/extensions/__init__.py
goalEDP/extensions/goal.py
goalEDP/extensions/index.css
goalEDP/extensions/index.js
goalEDP/extensions/indexTemplate.py
goalEDP/extensions/web_gui.py
goalEDP/storages/__init__.py
goalEDP/storages/in_memory.py
goaledp-0.1.1.dist-info/licenses/LICENSE
goaledp-0.1.1.dist-info/METADATA
goaledp-0.1.1.dist-info/WHEEL
goaledp-0.1.1.dist-info/top_level.txt
goaledp-0.1.1.dist-info/RECORD
