Metadata-Version: 2.4
Name: goalEDP
Version: 0.1.1
Summary: Library for processing goal-oriented agents. Processing is done on an event-driven mechanism. Events are saved to be used by explanation generating methods.
Author-email: Henrique Emanoel Viana <hv5088@gmail.com>
Project-URL: Homepage, https://github.com/hviana/goalEDP
Keywords: scientific,paradigms,agents,explainability
Classifier: Programming Language :: Python :: 3
Classifier: License :: OSI Approved :: MIT License
Classifier: Operating System :: OS Independent
Classifier: Topic :: Scientific/Engineering
Requires-Python: >=3.12
License-File: LICENSE
Requires-Dist: flask[async]
Requires-Dist: flask
Requires-Dist: nest_asyncio
Requires-Dist: uuid
Requires-Dist: deepdiff
Requires-Dist: requests
Dynamic: license-file
